djangosecretkeyenv-0.2.0.dist-info/licenses/LICENSE
seckeyenv/__init__.py
seckeyenv/management/__init__.py
seckeyenv/management/commands/__init__.py
seckeyenv/management/commands/secretkeyenv.py
djangosecretkeyenv-0.2.0.dist-info/METADATA
djangosecretkeyenv-0.2.0.dist-info/WHEEL
djangosecretkeyenv-0.2.0.dist-info/top_level.txt
djangosecretkeyenv-0.2.0.dist-info/RECORD
