Metadata-Version: 2.4
Name: djangosecretkeyenv
Version: 0.2.0
Summary: Django management command to generate SECRET_KEY and save it in .env
Author-email: Igor Usikow <usikowigor@gmail.com>
License: MIT
Requires-Python: >=3.14
License-File: LICENSE
Requires-Dist: build>=1.3.0
Requires-Dist: django>=5.2.7
Requires-Dist: twine>=6.2.0
Dynamic: license-file
